pic_cut/__init__.py
pic_cut-0.0.25.dist-info/LICENSE
pic_cut-0.0.25.dist-info/METADATA
pic_cut-0.0.25.dist-info/WHEEL
pic_cut-0.0.25.dist-info/top_level.txt
pic_cut-0.0.25.dist-info/RECORD
