Metadata-Version: 2.1
Name: pic-cut
Version: 0.0.25
Summary: Cut Long Picture.
Home-page: https://github.com/gaoyunzhi/pic_cut
Author: Yunzhi Gao
Author-email: gaoyunzhi@gmail.com
License: UNKNOWN
Platform: UNKNOWN
Classifier: Programming Language :: Python :: 3
Classifier: License :: OSI Approved :: MIT License
Classifier: Operating System :: OS Independent
Requires-Python: >=3.0
Requires-Dist: cached-url (>=0.0.8)
